AUTHORS
CHANGES
CHANGES.old
CODE_OF_CONDUCT
CONTRIBUTING.rst
EXAMPLES
LICENSE
MANIFEST.in
Makefile
README.rst
babel.cfg
setup.cfg
setup.py
tox.ini
GxSphinx.egg-info/PKG-INFO
GxSphinx.egg-info/SOURCES.txt
GxSphinx.egg-info/dependency_links.txt
GxSphinx.egg-info/entry_points.txt
GxSphinx.egg-info/not-zip-safe
GxSphinx.egg-info/requires.txt
GxSphinx.egg-info/top_level.txt
doc/Makefile
doc/changes.rst
doc/conf.py
doc/contents.rst
doc/develop.rst
doc/examples.rst
doc/faq.rst
doc/glossary.rst
doc/latex.rst
doc/make.bat
doc/templating.rst
doc/theming.rst
doc/_static/Makefile
doc/_static/bookcover.png
doc/_static/conf.py.txt
doc/_static/more.png
doc/_static/pocoo.png
doc/_static/sphinx.png
doc/_static/translation.puml
doc/_static/translation.svg
doc/_static/themes/agogo.png
doc/_static/themes/alabaster.png
doc/_static/themes/bizstyle.png
doc/_static/themes/classic.png
doc/_static/themes/haiku.png
doc/_static/themes/nature.png
doc/_static/themes/pyramid.png
doc/_static/themes/scrolls.png
doc/_static/themes/sphinx_rtd_theme.png
doc/_static/themes/sphinxdoc.png
doc/_static/themes/traditional.png
doc/_static/themes/fullsize/agogo.png
doc/_static/themes/fullsize/alabaster.png
doc/_static/themes/fullsize/bizstyle.png
doc/_static/themes/fullsize/classic.png
doc/_static/themes/fullsize/haiku.png
doc/_static/themes/fullsize/nature.png
doc/_static/themes/fullsize/pyramid.png
doc/_static/themes/fullsize/scrolls.png
doc/_static/themes/fullsize/sphinx_rtd_theme.png
doc/_static/themes/fullsize/sphinxdoc.png
doc/_static/themes/fullsize/traditional.png
doc/_templates/index.html
doc/_templates/indexsidebar.html
doc/_themes/sphinx13/layout.html
doc/_themes/sphinx13/theme.conf
doc/_themes/sphinx13/static/bodybg.png
doc/_themes/sphinx13/static/footerbg.png
doc/_themes/sphinx13/static/headerbg.png
doc/_themes/sphinx13/static/listitem.png
doc/_themes/sphinx13/static/relbg.png
doc/_themes/sphinx13/static/sphinx13.css
doc/_themes/sphinx13/static/sphinxheader.png
doc/development/index.rst
doc/development/tutorials/helloworld.rst
doc/development/tutorials/index.rst
doc/development/tutorials/recipe.rst
doc/development/tutorials/todo.rst
doc/development/tutorials/examples/README.rst
