Metadata-Version: 2.1
Name: GxSphinx
Version: 1.0.0
Summary: Python documentation generator
Home-page: http://sphinx-doc.org/
Author: Georg Brandl
Author-email: georg@python.org
License: BSD
Download-URL: https://pypi.org/project/Sphinx/
Project-URL: Code, https://github.com/sphinx-doc/sphinx
Project-URL: Issue tracker, https://github.com/sphinx-doc/sphinx/issues
Platform: any
Classifier: Development Status :: 5 - Production/Stable
Classifier: Environment :: Console
Classifier: Environment :: Web Environment
Classifier: Intended Audience :: Developers
Classifier: Intended Audience :: Education
Classifier: Intended Audience :: End Users/Desktop
Classifier: Intended Audience :: Science/Research
Classifier: Intended Audience :: System Administrators
Classifier: License :: OSI Approved :: BSD License
Classifier: Operating System :: OS Independent
Classifier: Programming Language :: Python
Classifier: Programming Language :: Python :: 3
Classifier: Programming Language :: Python :: 3 :: Only
Classifier: Programming Language :: Python :: 3.5
Classifier: Programming Language :: Python :: 3.6
Classifier: Programming Language :: Python :: 3.7
Classifier: Programming Language :: Python :: 3.8
Classifier: Programming Language :: Python :: Implementation :: CPython
Classifier: Programming Language :: Python :: Implementation :: PyPy
Classifier: Framework :: Setuptools Plugin
Classifier: Framework :: Sphinx
Classifier: Framework :: Sphinx :: Extension
Classifier: Framework :: Sphinx :: Theme
Classifier: Topic :: Documentation
Classifier: Topic :: Documentation :: Sphinx
Classifier: Topic :: Internet :: WWW/HTTP :: Site Management
Classifier: Topic :: Printing
Classifier: Topic :: Software Development
Classifier: Topic :: Software Development :: Documentation
Classifier: Topic :: Text Processing
Classifier: Topic :: Text Processing :: General
Classifier: Topic :: Text Processing :: Indexing
Classifier: Topic :: Text Processing :: Markup
Classifier: Topic :: Text Processing :: Markup :: HTML
Classifier: Topic :: Text Processing :: Markup :: LaTeX
Classifier: Topic :: Utilities
Requires-Python: >=3.5
Provides-Extra: docs
Provides-Extra: lint
Provides-Extra: test
